{"title":"It's Nice That","url":"https://www.itsnicethat.com/articles","favicon":"https://www.itsnicethat.com/favicon-32x32.png","elements":[{"title":"Steph Hardy’s abstract illustrations tell the secret inner lives of plants","contents":"<a class=\"block link-reset font-0 pt4 px4 sm-px4 md-px3 lg-px4\" href=\"/articles/steph-hardy-discover-illustration-160123\"><div class=\"relative overflow-hidden\"><div class=\"listing-item-image\" style=\"height:0;overflow:hidden;padding-bottom:100%;position:relative;width:100%\"><div style=\"bottom:0;left:0;position:absolute;right:0;top:0\"><div style=\"background-color:#ebe1d4;height:100%;opacity:1;position:absolute;transition:opacity 2s;width:100%\"></div></div></div></div></a><a class=\"block link-reset py4 px4 sm-px4 md-px3 lg-px4\" href=\"/articles/steph-hardy-discover-illustration-160123\"><h3 class=\"sans m0\" style=\"font-variation-settings:&quot;wght&quot; 30, &quot;stbl&quot; 100\"><span class=\"listing-item-title\">Steph Hardy’s abstract illustrations tell the secret inner lives of plants</span></h3><div class=\"h6 sans mt3 dove-grey first-cap\">10 hours ago</div></a>","link":"https://www.itsnicethat.com/articles/steph-hardy-discover-illustration-160123","retrieved":1673890381836},{"title":"From exhibitions to nail salons, Countach Studio caters its narrative-based designs to everyone","contents":"<a class=\"block link-reset font-0 pt4 px4 sm-px4 md-px3 lg-px4\" href=\"/articles/countach-studio-discover-graphic-design-160123\"><div class=\"relative overflow-hidden\"><div class=\"listing-item-image\" style=\"height:0;overflow:hidden;padding-bottom:144.82014388489208%;position:relative;width:100%\"><div style=\"bottom:0;left:0;position:absolute;right:0;top:0\"><div style=\"background-color:#c8b6b7;height:100%;opacity:1;position:absolute;transition:opacity 2s;width:100%\"></div></div></div></div></a><a class=\"block link-reset py4 px4 sm-px4 md-px3 lg-px4\" href=\"/articles/countach-studio-discover-graphic-design-160123\"><h3 class=\"sans m0\" style=\"font-variation-settings:&quot;wght&quot; 30, &quot;stbl&quot; 100\"><span class=\"listing-item-title\">From exhibitions to nail salons, Countach Studio caters its narrative-based designs to everyone</span></h3><div class=\"h6 sans mt3 dove-grey first-cap\">10 hours ago</div></a>","link":"https://www.itsnicethat.com/articles/countach-studio-discover-graphic-design-160123","retrieved":1673890381840},{"title":"How do you get José Mourinho to be in your music video? KLVDR reveals all","contents":"<a class=\"block link-reset font-0 pt4 px4 sm-px4 md-px3 lg-px4\" href=\"/articles/nicer-tuesdays-november-2022-klvdr-291122\"><div class=\"relative overflow-hidden\"><div class=\"listing-item-image\" style=\"height:0;overflow:hidden;padding-bottom:65.4696132596685%;position:relative;width:100%\"><div style=\"bottom:0;left:0;position:absolute;right:0;top:0\"><div style=\"background-color:#d5d5c4;height:100%;opacity:1;position:absolute;transition:opacity 2s;width:100%\"></div></div></div></div></a><a class=\"block link-reset py4 px4 sm-px4 md-px3 lg-px4\" href=\"/articles/nicer-tuesdays-november-2022-klvdr-291122\"><h3 class=\"sans m0\" style=\"font-variation-settings:&quot;wght&quot; 30, &quot;stbl&quot; 100\"><span class=\"listing-item-title\">How do you get José Mourinho to be in your music video? KLVDR reveals all</span></h3><div class=\"h6 sans mt3 dove-grey first-cap\">4 days ago</div></a>","link":"https://www.itsnicethat.com/articles/nicer-tuesdays-november-2022-klvdr-291122","retrieved":1673545460054},{"title":"Maram Al Rafaei creates a typeface inspired by cinematic emotion","contents":"<a class=\"block link-reset font-0 pt4 px4 sm-px4 md-px3 lg-px4\" href=\"/articles/maram-al-rafaei-project-graphic-design-120123\"><div class=\"relative overflow-hidden\"><div class=\"listing-item-image\" style=\"height:0;overflow:hidden;padding-bottom:100%;position:relative;width:100%\"><div style=\"bottom:0;left:0;position:absolute;right:0;top:0\"><div style=\"background-color:#7e8b7d;height:100%;opacity:1;position:absolute;transition:opacity 2s;width:100%\"></div></div></div></div></a><a class=\"block link-reset py4 px4 sm-px4 md-px3 lg-px4\" href=\"/articles/maram-al-rafaei-project-graphic-design-120123\"><h3 class=\"sans m0\" style=\"font-variation-settings:&quot;wght&quot; 30, &quot;stbl&quot; 100\"><span class=\"listing-item-title\">Maram Al Rafaei creates a typeface inspired by cinematic emotion</span></h3><div class=\"h6 sans mt3 dove-grey first-cap\">4 days ago</div></a>","link":"https://www.itsnicethat.com/articles/maram-al-rafaei-project-graphic-design-120123","retrieved":1673545460054},{"title":"João Gonzalez’s animated short is a frosty tale of love, loss and fatherly affection","contents":"<a class=\"block link-reset font-0 pt4 px4 sm-px4 md-px3 lg-px4\" href=\"/articles/joao-gonzalez-ice-merchants-project-animation-120123\"><div class=\"relative overflow-hidden\"><div class=\"listing-item-image\" style=\"height:0;overflow:hidden;padding-bottom:52.75%;position:relative;width:100%\"><div style=\"bottom:0;left:0;position:absolute;right:0;top:0\"><div style=\"background-color:#c3b4a0;height:100%;opacity:1;position:absolute;transition:opacity 2s;width:100%\"></div></div></div></div></a><a class=\"block link-reset py4 px4 sm-px4 md-px3 lg-px4\" href=\"/articles/joao-gonzalez-ice-merchants-project-animation-120123\"><h3 class=\"sans m0\" style=\"font-variation-settings:&quot;wght&quot; 30, &quot;stbl&quot; 100\"><span class=\"listing-item-title\">João Gonzalez’s animated short is a frosty tale of love, loss and fatherly affection</span></h3><div class=\"h6 sans mt3 dove-grey first-cap\">4 days ago</div></a>","link":"https://www.itsnicethat.com/articles/joao-gonzalez-ice-merchants-project-animation-120123","retrieved":1673545460057},{"title":"Chasing golden hour, Charlotte Ellis captures Oaxaca’s tribute to the Virgin of Guadalupe","contents":"<a class=\"block link-reset font-0 pt4 px4 sm-px4 md-px3 lg-px4\" href=\"/articles/charlotte-ellis-celebrating-the-virgin-of-guadalupe-project-photography-110123\"><div class=\"relative overflow-hidden\"><div class=\"listing-item-image\" style=\"height:0;overflow:hidden;padding-bottom:116.68526785714286%;position:relative;width:100%\"><div style=\"bottom:0;left:0;position:absolute;right:0;top:0\"><div style=\"background-color:#cccac7;height:100%;opacity:1;position:absolute;transition:opacity 2s;width:100%\"></div></div></div></div></a><a class=\"block link-reset py4 px4 sm-px4 md-px3 lg-px4\" href=\"/articles/charlotte-ellis-celebrating-the-virgin-of-guadalupe-project-photography-110123\"><h3 class=\"sans m0\" style=\"font-variation-settings:&quot;wght&quot; 30, &quot;stbl&quot; 100\"><span class=\"listing-item-title\">Chasing golden hour, Charlotte Ellis captures Oaxaca’s tribute to the Virgin of Guadalupe</span></h3><div class=\"h6 sans mt3 dove-grey first-cap\">5 days ago</div></a>","link":"https://www.itsnicethat.com/articles/charlotte-ellis-celebrating-the-virgin-of-guadalupe-project-photography-110123","retrieved":1673479493107},{"title":"Tae Lee sees their peaceful artworks as an offering to those living through uncertain times","contents":"<a class=\"block link-reset font-0 pt4 px4 sm-px4 md-px3 lg-px4\" href=\"/articles/tae-lee-discover-art-110123\"><div class=\"relative overflow-hidden\"><div class=\"listing-item-image\" style=\"height:0;overflow:hidden;padding-bottom:110.99644128113879%;position:relative;width:100%\"><div style=\"bottom:0;left:0;position:absolute;right:0;top:0\"><div style=\"background-color:#0f1f19;height:100%;opacity:1;position:absolute;transition:opacity 2s;width:100%\"></div></div></div></div></a><a class=\"block link-reset py4 px4 sm-px4 md-px3 lg-px4\" href=\"/articles/tae-lee-discover-art-110123\"><h3 class=\"sans m0\" style=\"font-variation-settings:&quot;wght&quot; 30, &quot;stbl&quot; 100\"><span class=\"listing-item-title\">Tae Lee sees their peaceful artworks as an offering to those living through uncertain times</span></h3><div class=\"h6 sans mt3 dove-grey first-cap\">5 days ago</div></a>","link":"https://www.itsnicethat.com/articles/tae-lee-discover-art-110123","retrieved":1673479493107},{"title":"Cash & Carry is the one-woman studio channelling punk and railing against boredom","contents":"<a class=\"block link-reset font-0 pt4 px4 sm-px4 md-px3 lg-px4\" href=\"/articles/cash-and-carry-disover-graphic-design-110123\"><div class=\"relative overflow-hidden\"><div class=\"listing-item-image\" style=\"height:0;overflow:hidden;padding-bottom:71.45682267633488%;position:relative;width:100%\"><div style=\"bottom:0;left:0;position:absolute;right:0;top:0\"><div style=\"background-color:#f91388;height:100%;opacity:1;position:absolute;transition:opacity 2s;width:100%\"></div></div></div></div></a><a class=\"block link-reset py4 px4 sm-px4 md-px3 lg-px4\" href=\"/articles/cash-and-carry-disover-graphic-design-110123\"><h3 class=\"sans m0\" style=\"font-variation-settings:&quot;wght&quot; 30, &quot;stbl&quot; 100\"><span class=\"listing-item-title\">Cash &amp; Carry is the one-woman studio channelling punk and railing against boredom</span></h3><div class=\"h6 sans mt3 dove-grey first-cap\">5 days ago</div></a>","link":"https://www.itsnicethat.com/articles/cash-and-carry-disover-graphic-design-110123","retrieved":1673479493108},{"title":"With cuteness and crayons, Shiori Tamura makes everyday moments a little more special","contents":"<a class=\"block link-reset font-0 pt4 px4 sm-px4 md-px3 lg-px4\" href=\"/articles/shiori-tamura-discover-illustration-100123\"><div class=\"relative overflow-hidden\"><div class=\"listing-item-image\" style=\"height:0;overflow:hidden;padding-bottom:100%;position:relative;width:100%\"><div style=\"bottom:0;left:0;position:absolute;right:0;top:0\"><div style=\"background-color:#fa4d39;height:100%;opacity:1;position:absolute;transition:opacity 2s;width:100%\"></div></div></div></div></a><a class=\"block link-reset py4 px4 sm-px4 md-px3 lg-px4\" href=\"/articles/shiori-tamura-discover-illustration-100123\"><h3 class=\"sans m0\" style=\"font-variation-settings:&quot;wght&quot; 30, &quot;stbl&quot; 100\"><span class=\"listing-item-title\">With cuteness and crayons, Shiori Tamura makes everyday moments a little more special</span></h3><div class=\"h6 sans mt3 dove-grey first-cap\">6 days ago</div></a>","link":"https://www.itsnicethat.com/articles/shiori-tamura-discover-illustration-100123","retrieved":1673479493108},{"title":"A whirlwind tour of global creativity, Crack Magazine returns with its bi-annual publication","contents":"<a class=\"block link-reset font-0 pt4 px4 sm-px4 md-px3 lg-px4\" href=\"/articles/crack-magazine-the-collections-volume-iv-project-publication-100123\"><div class=\"relative overflow-hidden\"><div class=\"listing-item-image\" style=\"height:0;overflow:hidden;padding-bottom:69.00931414055886%;position:relative;width:100%\"><div style=\"bottom:0;left:0;position:absolute;right:0;top:0\"><div style=\"background-color:#1d181b;height:100%;opacity:1;position:absolute;transition:opacity 2s;width:100%\"></div></div></div></div></a><a class=\"block link-reset py4 px4 sm-px4 md-px3 lg-px4\" href=\"/articles/crack-magazine-the-collections-volume-iv-project-publication-100123\"><h3 class=\"sans m0\" style=\"font-variation-settings:&quot;wght&quot; 30, &quot;stbl&quot; 100\"><span class=\"listing-item-title\">A whirlwind tour of global creativity, Crack Magazine returns with its bi-annual publication</span></h3><div class=\"h6 sans mt3 dove-grey first-cap\">6 days ago</div></a>","link":"https://www.itsnicethat.com/articles/crack-magazine-the-collections-volume-iv-project-publication-100123","retrieved":1673479493109},{"title":"Food, music and human connection fuel the colourful world of Réplica studio","contents":"<a class=\"block link-reset font-0 pt4 px4 sm-px4 md-px3 lg-px4\" href=\"/articles/replica-discover-graphic-design-090123\"><div class=\"relative overflow-hidden\"><div class=\"listing-item-image\" style=\"height:0;overflow:hidden;padding-bottom:125%;position:relative;width:100%\"><div style=\"bottom:0;left:0;position:absolute;right:0;top:0\"><div style=\"background-color:#f2403b;height:100%;opacity:1;position:absolute;transition:opacity 2s;width:100%\"></div></div></div></div></a><a class=\"block link-reset py4 px4 sm-px4 md-px3 lg-px4\" href=\"/articles/replica-discover-graphic-design-090123\"><h3 class=\"sans m0\" style=\"font-variation-settings:&quot;wght&quot; 30, &quot;stbl&quot; 100\"><span class=\"listing-item-title\">Food, music and human connection fuel the colourful world of Réplica studio</span></h3><div class=\"h6 sans mt3 dove-grey first-cap\">7 days ago</div></a>","link":"https://www.itsnicethat.com/articles/replica-discover-graphic-design-090123","retrieved":1673479493109},{"title":"Sexy, lurid and satirical: Elizabeth Renstrom’s rose-tinted photography hides a deeper meaning","contents":"<a class=\"block link-reset font-0 pt4 px4 sm-px4 md-px3 lg-px4\" href=\"/articles/elizabeth-renstrom-discover-photography-090123\"><div class=\"relative overflow-hidden\"><div class=\"listing-item-image\" style=\"height:0;overflow:hidden;padding-bottom:63.11953352769679%;position:relative;width:100%\"><div style=\"bottom:0;left:0;position:absolute;right:0;top:0\"><div style=\"background-color:#ead2d9;height:100%;opacity:1;position:absolute;transition:opacity 2s;width:100%\"></div></div></div></div></a><a class=\"block link-reset py4 px4 sm-px4 md-px3 lg-px4\" href=\"/articles/elizabeth-renstrom-discover-photography-090123\"><h3 class=\"sans m0\" style=\"font-variation-settings:&quot;wght&quot; 30, &quot;stbl&quot; 100\"><span class=\"listing-item-title\">Sexy, lurid and satirical: Elizabeth Renstrom’s rose-tinted photography hides a deeper meaning</span></h3><div class=\"h6 sans mt3 dove-grey first-cap\">7 days ago</div></a>","link":"https://www.itsnicethat.com/articles/elizabeth-renstrom-discover-photography-090123","retrieved":1673479493109},{"title":"Photographer Rosie Foster is interested in finding the beauty of personal spaces","contents":"<a class=\"block link-reset font-0 pt4 px4 sm-px4 md-px3 lg-px4\" href=\"/articles/rosie-foster-at-home-project-photography-050123\"><div class=\"relative overflow-hidden\"><div class=\"listing-item-image\" style=\"height:0;overflow:hidden;padding-bottom:122.53521126760563%;position:relative;width:100%\"><div style=\"bottom:0;left:0;position:absolute;right:0;top:0\"><div style=\"background-color:#c7c1bd;height:100%;opacity:1;position:absolute;transition:opacity 2s;width:100%\"></div></div></div></div></a><a class=\"block link-reset py4 px4 sm-px4 md-px3 lg-px4\" href=\"/articles/rosie-foster-at-home-project-photography-050123\"><h3 class=\"sans m0\" style=\"font-variation-settings:&quot;wght&quot; 30, &quot;stbl&quot; 100\"><span class=\"listing-item-title\">Photographer Rosie Foster is interested in finding the beauty of personal spaces</span></h3><div class=\"h6 sans mt3 dove-grey first-cap\">11 days ago</div></a>","link":"https://www.itsnicethat.com/articles/rosie-foster-at-home-project-photography-050123","retrieved":1673479493114},{"title":"Sid Lee joins with the Ellen MacArthur Foundation in a book showcasing the potential of circular fashion","contents":"<a class=\"block link-reset font-0 pt4 px4 sm-px4 md-px3 lg-px4\" href=\"/articles/sid-lee-circular-design-for-fashion-project-publication-050123\"><div class=\"relative overflow-hidden\"><div class=\"relative font-0 line-height-0\"></div></div></a><a class=\"block link-reset py4 px4 sm-px4 md-px3 lg-px4\" href=\"/articles/sid-lee-circular-design-for-fashion-project-publication-050123\"><h3 class=\"sans m0\" style=\"font-variation-settings:&quot;wght&quot; 30, &quot;stbl&quot; 100\"><span class=\"listing-item-title\">Sid Lee joins with the Ellen MacArthur Foundation in a book showcasing the potential of circular fashion</span></h3><div class=\"h6 sans mt3 dove-grey first-cap\">11 days ago</div></a>","link":"https://www.itsnicethat.com/articles/sid-lee-circular-design-for-fashion-project-publication-050123","retrieved":1673479493121},{"title":"Kin Coedel photographs tranquil moments of everyday life in Tibet","contents":"<a class=\"block link-reset font-0 pt4 px4 sm-px4 md-px3 lg-px4\" href=\"/articles/kin-coedel-project-dyal-thak-photography-040123\"><div class=\"relative overflow-hidden\"><div class=\"listing-item-image\" style=\"height:0;overflow:hidden;padding-bottom:80%;position:relative;width:100%\"><div style=\"bottom:0;left:0;position:absolute;right:0;top:0\"><div style=\"background-color:#b1a4a5;height:100%;opacity:1;position:absolute;transition:opacity 2s;width:100%\"></div></div></div></div></a><a class=\"block link-reset py4 px4 sm-px4 md-px3 lg-px4\" href=\"/articles/kin-coedel-project-dyal-thak-photography-040123\"><h3 class=\"sans m0\" style=\"font-variation-settings:&quot;wght&quot; 30, &quot;stbl&quot; 100\"><span class=\"listing-item-title\">Kin Coedel photographs tranquil moments of everyday life in Tibet</span></h3><div class=\"h6 sans mt3 dove-grey first-cap\">12 days ago</div></a>","link":"https://www.itsnicethat.com/articles/kin-coedel-project-dyal-thak-photography-040123","retrieved":1673479493124},{"title":"Using Y2K aesthetics Mojo Supermarket gives Girls Who Code a perfectly pixelated brand refresh","contents":"<a class=\"block link-reset font-0 pt4 px4 sm-px4 md-px3 lg-px4\" href=\"/articles/mojo-supermarket-girls-who-code-graphic-design-030123\"><div class=\"relative overflow-hidden\"><div class=\"listing-item-image\" style=\"height:0;overflow:hidden;padding-bottom:56.24444444444444%;position:relative;width:100%\"><div style=\"bottom:0;left:0;position:absolute;right:0;top:0\"><div style=\"background-color:#d86ab9;height:100%;opacity:1;position:absolute;transition:opacity 2s;width:100%\"></div></div></div></div></a><a class=\"block link-reset py4 px4 sm-px4 md-px3 lg-px4\" href=\"/articles/mojo-supermarket-girls-who-code-graphic-design-030123\"><h3 class=\"sans m0\" style=\"font-variation-settings:&quot;wght&quot; 30, &quot;stbl&quot; 100\"><span class=\"listing-item-title\">Using Y2K aesthetics Mojo Supermarket gives Girls Who Code a perfectly pixelated brand refresh</span></h3><div class=\"h6 sans mt3 dove-grey first-cap\">13 days ago</div></a>","link":"https://www.itsnicethat.com/articles/mojo-supermarket-girls-who-code-graphic-design-030123","retrieved":1673479493130},{"title":"The Bad Thing is a comic about a dog who feels morally conflicted over killing birds","contents":"<a class=\"block link-reset font-0 pt4 px4 sm-px4 md-px3 lg-px4\" href=\"/articles/maisie-cowell-the-bad-thing-illustration-030123\"><div class=\"relative overflow-hidden\"><div class=\"listing-item-image\" style=\"height:0;overflow:hidden;padding-bottom:79.97111218103034%;position:relative;width:100%\"><div style=\"bottom:0;left:0;position:absolute;right:0;top:0\"><div style=\"background-color:#3d56b5;height:100%;opacity:1;position:absolute;transition:opacity 2s;width:100%\"></div></div></div></div></a><a class=\"block link-reset py4 px4 sm-px4 md-px3 lg-px4\" href=\"/articles/maisie-cowell-the-bad-thing-illustration-030123\"><h3 class=\"sans m0\" style=\"font-variation-settings:&quot;wght&quot; 30, &quot;stbl&quot; 100\"><span class=\"listing-item-title\">The Bad Thing is a comic about a dog who feels morally conflicted over killing birds</span></h3><div class=\"h6 sans mt3 dove-grey first-cap\">13 days ago</div></a>","link":"https://www.itsnicethat.com/articles/maisie-cowell-the-bad-thing-illustration-030123","retrieved":1673479493132},{"title":"Slick, playful and graphically precise: Cairo-based studio Ntsal puts quality and communication first","contents":"<a class=\"block link-reset font-0 pt4 px4 sm-px4 md-px3 lg-px4\" href=\"/articles/ntsal-discover-graphic-design-030123\"><div class=\"relative overflow-hidden\"><div class=\"listing-item-image\" style=\"height:0;overflow:hidden;padding-bottom:140.81748509792791%;position:relative;width:100%\"><div style=\"bottom:0;left:0;position:absolute;right:0;top:0\"><div style=\"background-color:#f7f7f7;height:100%;opacity:1;position:absolute;transition:opacity 2s;width:100%\"></div></div></div></div></a><a class=\"block link-reset py4 px4 sm-px4 md-px3 lg-px4\" href=\"/articles/ntsal-discover-graphic-design-030123\"><h3 class=\"sans m0\" style=\"font-variation-settings:&quot;wght&quot; 30, &quot;stbl&quot; 100\"><span class=\"listing-item-title\">Slick, playful and graphically precise: Cairo-based studio Ntsal puts quality and communication first</span></h3><div class=\"h6 sans mt3 dove-grey first-cap\">13 days ago</div></a>","link":"https://www.itsnicethat.com/articles/ntsal-discover-graphic-design-030123","retrieved":1673479493132},{"title":"Discover a special Mediterranean jetty with photographer Miro Lovejoy Teplitzky","contents":"<a class=\"block link-reset font-0 pt4 px4 sm-px4 md-px3 lg-px4\" href=\"/articles/miro-lovejoy-teplitzky-youth-project-photography-030123\"><div class=\"relative overflow-hidden\"><div class=\"listing-item-image\" style=\"height:0;overflow:hidden;padding-bottom:123.30456226880395%;position:relative;width:100%\"><div style=\"bottom:0;left:0;position:absolute;right:0;top:0\"><div style=\"background-color:#d6a370;height:100%;opacity:1;position:absolute;transition:opacity 2s;width:100%\"></div></div></div></div></a><a class=\"block link-reset py4 px4 sm-px4 md-px3 lg-px4\" href=\"/articles/miro-lovejoy-teplitzky-youth-project-photography-030123\"><h3 class=\"sans m0\" style=\"font-variation-settings:&quot;wght&quot; 30, &quot;stbl&quot; 100\"><span class=\"listing-item-title\">Discover a special Mediterranean jetty with photographer Miro Lovejoy Teplitzky</span></h3><div class=\"h6 sans mt3 dove-grey first-cap\">13 days ago</div></a>","link":"https://www.itsnicethat.com/articles/miro-lovejoy-teplitzky-youth-project-photography-030123","retrieved":1673479493132},{"title":"In Creators Crushing It, Pinterest shares the stories of some of its most passionate creators","contents":"<a class=\"block link-reset font-0 pt4 px4 sm-px4 md-px3 lg-px4\" href=\"/articles/pinterest-creators-crushing-it-creative-industry-sponsored-content-191222\"><div class=\"relative overflow-hidden\"><div class=\"listing-item-image\" style=\"height:0;overflow:hidden;padding-bottom:100%;position:relative;width:100%\"><div style=\"bottom:0;left:0;position:absolute;right:0;top:0\"><div style=\"background-color:#ede4d3;height:100%;opacity:1;position:absolute;transition:opacity 2s;width:100%\"></div></div></div></div></a><a class=\"block link-reset py4 px4 sm-px4 md-px3 lg-px4\" href=\"/articles/pinterest-creators-crushing-it-creative-industry-sponsored-content-191222\"><h3 class=\"sans m0\" style=\"font-variation-settings:&quot;wght&quot; 30, &quot;stbl&quot; 100\"><span class=\"listing-item-title\">In Creators Crushing It, Pinterest shares the stories of some of its most passionate creators</span></h3><div class=\"h6 sans mt3 dove-grey first-cap\">19 December 2022</div></a>","link":"https://www.itsnicethat.com/articles/pinterest-creators-crushing-it-creative-industry-sponsored-content-191222","retrieved":1673479493133}]}